gpu_tpu_lab_server/__init__.py
gpu_tpu_lab_server/_nbdev.py
gpu_tpu_lab_server/core.py
gpu_tpu_lab_server-0.0.6.dist-info/LICENSE
gpu_tpu_lab_server-0.0.6.dist-info/METADATA
gpu_tpu_lab_server-0.0.6.dist-info/WHEEL
gpu_tpu_lab_server-0.0.6.dist-info/entry_points.txt
gpu_tpu_lab_server-0.0.6.dist-info/top_level.txt
gpu_tpu_lab_server-0.0.6.dist-info/RECORD
