Metadata-Version: 2.1
Name: gpu-tpu-lab-server
Version: 0.0.6
Summary: Running a jupyter lab or vs code server environment from colab with google drive support
Home-page: https://github.com/fastdaima/gpu_tpu_lab_server/tree/main/
Author: fastdaima
Author-email: sivaramakrishnang25@gmail.com
License: Apache Software License 2.0
Keywords: nbdev
Platform: UNKNOWN
Classifier: Development Status :: 3 - Alpha
Classifier: Intended Audience :: Developers
Classifier: Natural Language :: English
Classifier: Programming Language :: Python :: 3.6
Classifier: Programming Language :: Python :: 3.7
Classifier: Programming Language :: Python :: 3.8
Classifier: License :: OSI Approved :: Apache Software License
Requires-Python: >=3.6
Requires-Dist: pip
Requires-Dist: packaging
Provides-Extra: dev
